joblet/__init__.py
joblet/cli.py
joblet/common.py
joblet/http.py
kneo_joblet-0.1.0.dist-info/licenses/LICENSE.txt
kneo_joblet-0.1.0.dist-info/METADATA
kneo_joblet-0.1.0.dist-info/WHEEL
kneo_joblet-0.1.0.dist-info/entry_points.txt
kneo_joblet-0.1.0.dist-info/top_level.txt
kneo_joblet-0.1.0.dist-info/RECORD
