Metadata-Version: 2.4
Name: kneo-joblet
Version: 0.1.0
Summary: KNeo Serverless Job
Author-email: Marian Neagul <mneagul@gmail.com>, Vasile Craciunescu <vasile.craciunescu@terrasigna.com>
License-Expression: Apache-2.0
Requires-Python: >=3.10
License-File: LICENSE.txt
Requires-Dist: cloudevents>=1.12.0
Requires-Dist: fastapi<0.117.0,>=0.116.1
Requires-Dist: pydantic>=2.11.7
Requires-Dist: requests<3.0.0,>=2.32.4
Requires-Dist: uvicorn>=0.35.0
Dynamic: license-file
